ByteLightProject/__init__.py
ByteLightProject/module.py
bytelightproject-2.6.dist-info/LICENSE
bytelightproject-2.6.dist-info/METADATA
bytelightproject-2.6.dist-info/WHEEL
bytelightproject-2.6.dist-info/top_level.txt
bytelightproject-2.6.dist-info/RECORD
