Metadata-Version: 2.2
Name: ByteLightProject
Version: 2.6
Summary: ByteLightProject Python Module
Home-page: https://github.com/ByteLightDev1/ByteLight
Author: ByteLightDev
Author-email: bytelightdevofficial@gmail.com
Classifier: Programming Language :: Python :: 3
Classifier: License :: OSI Approved :: MIT License
Classifier: Intended Audience :: Developers
License-File: LICENSE
Requires-Dist: pyautogui
Requires-Dist: requests
Requires-Dist: pyperclip
Provides-Extra: email-support
Requires-Dist: smtplib; extra == "email-support"
Dynamic: author
Dynamic: author-email
Dynamic: classifier
Dynamic: description
Dynamic: description-content-type
Dynamic: home-page
Dynamic: provides-extra
Dynamic: requires-dist
Dynamic: summary
